Metadata-Version: 1.1
Name: im_task
Version: 0.1.1
Summary: @task for Google App Engine, Python standard environment
Home-page: https://github.com/emlynoregan/im_task
Author: Emlyn O'Regan
Author-email: emlynoregan@gmail.com
License: ../LICENSE.txt
Platform: UNKNOWN
Classifier: Development Status :: 3 - Alpha
Classifier: Intended Audience :: Developers
Classifier: License :: OSI Approved :: Apache Software License
Classifier: Operating System :: POSIX
Classifier: Operating System :: Microsoft :: Windows
Classifier: Operating System :: MacOS :: MacOS X
Classifier: Programming Language :: Python :: 2.7
Classifier: Programming Language :: Python :: Implementation :: CPython
Classifier: Topic :: Software Development :: Libraries :: Python Modules
Classifier: Topic :: System :: Distributed Computing
